pytorch_models-0.2.8.data/scripts/scaffold
torchmodels/__init__.py
torchmodels/common.py
torchmodels/manager.py
torchmodels/utils.py
torchmodels/modules/__init__.py
torchmodels/modules/activation.py
torchmodels/modules/attention.py
torchmodels/modules/embedding.py
torchmodels/modules/feedforward.py
torchmodels/modules/gaussian.py
torchmodels/modules/nonlinear.py
torchmodels/modules/pooling.py
torchmodels/modules/relational.py
torchmodels/modules/rnn.py
pytorch_models-0.2.8.dist-info/LICENSE
pytorch_models-0.2.8.dist-info/METADATA
pytorch_models-0.2.8.dist-info/WHEEL
pytorch_models-0.2.8.dist-info/top_level.txt
pytorch_models-0.2.8.dist-info/RECORD
