Metadata-Version: 2.1
Name: pytorch-models
Version: 0.2.8
Summary: A thin wrapper for scriptable PyTorch modules
Home-page: https://github.com/kaniblu/pytorch-models
Author: Kang Min Yoo
Author-email: kaniblurous@gmail.com
License: MIT
Platform: Operating System :: MacOS :: MacOS X
Platform: Operating System :: POSIX :: Linux
Classifier: Environment :: Console
Classifier: Intended Audience :: Developers
Classifier: Programming Language :: Java
Classifier: Programming Language :: Python
Requires-Dist: torch (>=1)
Requires-Dist: pyyaml
Requires-Dist: tqdm
